Topsis/Rajat.py
topsis_RajatGupta_101703427-1.0.0.dist-info/LICENSE.txt
topsis_RajatGupta_101703427-1.0.0.dist-info/METADATA
topsis_RajatGupta_101703427-1.0.0.dist-info/WHEEL
topsis_RajatGupta_101703427-1.0.0.dist-info/entry_points.txt
topsis_RajatGupta_101703427-1.0.0.dist-info/top_level.txt
topsis_RajatGupta_101703427-1.0.0.dist-info/RECORD
