Metadata-Version: 2.1
Name: topsis-RajatGupta-101703427
Version: 1.0.0
Summary: A python package to identify the best model out of different models using TOPSIS
Home-page: UNKNOWN
Author: Rajat Gupta
Author-email: rgupta2_be17@thapar.edu
License: UNKNOWN
Platform: UNKNOWN
Classifier: Programming Language :: Python :: 3
Classifier: License :: OSI Approved :: MIT License
Classifier: Operating System :: OS Independent
Requires-Python: >=3.6
Requires-Dist: requests
